spateo/__init__.py
spateo/align.py
spateo/configuration.py
spateo/cs.py
spateo/data_io.py
spateo/dd.py
spateo/errors.py
spateo/get_version.py
spateo/logging.py
spateo/pl.py
spateo/pp.py
spateo/sample_data.py
spateo/svg.py
spateo/tdr.py
spateo/tl.py
spateo/utils.py
spateo/warnings.py
spateo/alignment/__init__.py
spateo/alignment/deformation.py
spateo/alignment/morpho_alignment.py
spateo/alignment/paste_alignment.py
spateo/alignment/transform.py
spateo/alignment/utils.py
spateo/alignment/methods/__init__.py
spateo/alignment/methods/backend.py
spateo/alignment/methods/backend_ot.py
spateo/alignment/methods/deprecated_morpho.py
spateo/alignment/methods/deprecated_morpho_sparse.py
spateo/alignment/methods/deprecated_morpho_sparse_utils.py
spateo/alignment/methods/deprecated_utils.py
spateo/alignment/methods/mesh_correction_utils.py
spateo/alignment/methods/morpho_class.py
spateo/alignment/methods/morpho_mesh_correction.py
spateo/alignment/methods/paste.py
spateo/alignment/methods/sampling.py
spateo/alignment/methods/utils.py
spateo/digitization/__init__.py
spateo/digitization/borderline.py
spateo/digitization/boundary_old.py
spateo/digitization/contour.py
spateo/digitization/grid.py
spateo/digitization/utils.py
spateo/digitization/utils_old.py
spateo/external/__init__.py
spateo/external/lack.py
spateo/external/CAST/CAST_Mark.py
spateo/external/CAST/CAST_Projection.py
spateo/external/CAST/CAST_Stack.py
spateo/external/CAST/__init__.py
spateo/external/CAST/main.py
spateo/external/CAST/utils.py
spateo/external/CAST/visualize.py
spateo/external/CAST/model/__init__.py
spateo/external/CAST/model/aug.py
spateo/external/CAST/model/model_GCNII.py
spateo/external/STAGATE_pyG/STAGATE.py
spateo/external/STAGATE_pyG/Train_STAGATE.py
spateo/external/STAGATE_pyG/__init__.py
spateo/external/STAGATE_pyG/gat_conv.py
spateo/external/STAGATE_pyG/utils.py
spateo/io/__init__.py
spateo/io/bbs.py
spateo/io/bgi.py
spateo/io/image.py
spateo/io/image_utils.py
spateo/io/merfish.py
spateo_release-1.1.1.dist-info/LICENSE
spateo_release-1.1.1.dist-info/METADATA
spateo_release-1.1.1.dist-info/WHEEL
spateo_release-1.1.1.dist-info/top_level.txt
spateo_release-1.1.1.dist-info/RECORD
