Metadata-Version: 2.2
Name: spateo-release
Version: 1.1.1
Summary: Spatiotemporal modeling of molecular holograms
Home-page: https://github.com/aristoteleo/spateo-release
Author: Xiaojie Qiu
Author-email: xqiu@wi.mit.edu
License: BSD
Keywords: spatial-transcriptomics,stereo-seq,Visium,seqFish,MERFISH,slide-seq,DBiT-seq,HDST-seq,osmFISH,spatiotemporal
Classifier: Development Status :: 4 - Beta
Classifier: Programming Language :: Python :: 3.7
Classifier: Programming Language :: Python :: 3.8
Classifier: Programming Language :: Python :: 3.9
Classifier: Programming Language :: Python :: 3.10
Classifier: License :: OSI Approved :: BSD License
Classifier: Operating System :: OS Independent
Classifier: Topic :: Scientific/Engineering :: Bio-Informatics
Classifier: Topic :: Scientific/Engineering :: Image Processing
Requires-Python: >=3.7
License-File: LICENSE
Requires-Dist: adjustText
Requires-Dist: anndata>=0.8.0
Requires-Dist: colorcet>=2.0.1
Requires-Dist: csbdeep>=0.6.3
Requires-Dist: descartes
Requires-Dist: dynamo-release>=1.4.1
Requires-Dist: folium>=0.12.1
Requires-Dist: geopandas>=0.10.2
Requires-Dist: gpytorch
Requires-Dist: ipywidgets>=7.7.1
Requires-Dist: kneed>=0.7.0
Requires-Dist: kornia>=0.6.4
Requires-Dist: leidenalg>=0.10.0
Requires-Dist: loompy>=3.0.5
Requires-Dist: mapclassify>=2.4.2
Requires-Dist: matplotlib>=3.7.5
Requires-Dist: nbconvert
Requires-Dist: networkx>=2.6.3
Requires-Dist: numba>=0.46.0
Requires-Dist: numpy>=1.18.1
Requires-Dist: opencv-python>=4.5.4.60
Requires-Dist: pandas>=0.25.1
Requires-Dist: plotly>=5.1.0
Requires-Dist: POT>=0.8.1
Requires-Dist: psutil>=5.6.3
Requires-Dist: pynndescent>=0.4.8
Requires-Dist: pysal>=1.14.4
Requires-Dist: pyro-ppl
Requires-Dist: python-igraph>=0.7.1
Requires-Dist: pyvista>=0.39.1
Requires-Dist: scipy>=1.0
Requires-Dist: scikit-image>=0.18.0
Requires-Dist: scikit-learn>=0.19.1
Requires-Dist: seaborn>=0.9.0
Requires-Dist: setuptools>=58.0.4
Requires-Dist: Shapely>=1.8.0
Requires-Dist: statsmodels>=0.9.0
Requires-Dist: tqdm>=4.62.3
Requires-Dist: torch
Requires-Dist: trame>=2.2.5
Requires-Dist: trame-server>=2.7.0
Requires-Dist: typing_extensions>=4.0.1
Requires-Dist: umap-learn>=0.5.1
Requires-Dist: vtk>=9.2.2
Provides-Extra: dev
Requires-Dist: black==22.3.0; extra == "dev"
Requires-Dist: bumpversion>=0.6.0; extra == "dev"
Requires-Dist: coverage>=5.1; extra == "dev"
Requires-Dist: cython>=0.29.10; extra == "dev"
Requires-Dist: isort==5.10.1; extra == "dev"
Requires-Dist: nose>=1.3.7; extra == "dev"
Requires-Dist: numpy>=1.18.1; extra == "dev"
Requires-Dist: pre-commit>=2.4.0; extra == "dev"
Requires-Dist: setuptools>=42; extra == "dev"
Requires-Dist: sphinx>=3.3.1; extra == "dev"
Requires-Dist: sphinx-autoapi>=1.5.1; extra == "dev"
Requires-Dist: sphinx_rtd_theme>=0.5.0; extra == "dev"
Requires-Dist: twine>=2.0.0; extra == "dev"
Requires-Dist: wheel>=0.34.2; extra == "dev"
Provides-Extra: docs
Requires-Dist: sphinx_rtd_theme>=0.3.1; extra == "docs"
Requires-Dist: sphinx>=2.0.1; extra == "docs"
Requires-Dist: nbsphinx; extra == "docs"
Requires-Dist: sphinx-autodoc-typehints==1.17.0; extra == "docs"
Requires-Dist: nbsphinx-link; extra == "docs"
Requires-Dist: ipython; extra == "docs"
Requires-Dist: scanpydoc>=0.4.5; extra == "docs"
Requires-Dist: furo>=2020.12.30b24; extra == "docs"
Requires-Dist: typing_extensions; python_version < "3.8" and extra == "docs"
Requires-Dist: sphinx_copybutton; extra == "docs"
Requires-Dist: sphinx-gallery<0.10.1; extra == "docs"
Requires-Dist: sphinx-remove-toctrees; extra == "docs"
Requires-Dist: sphinx-design; extra == "docs"
Requires-Dist: sphinxext-opengraph==0.8.2; extra == "docs"
Requires-Dist: sphinx-autoapi; extra == "docs"
Requires-Dist: gitpython; extra == "docs"
Requires-Dist: myst-parser; extra == "docs"
Requires-Dist: pandoc; extra == "docs"
Provides-Extra: 3d
Requires-Dist: colorcet; extra == "3d"
Requires-Dist: ipygany; extra == "3d"
Requires-Dist: ipyvtklink; extra == "3d"
Requires-Dist: meshio; extra == "3d"
Requires-Dist: open3d>=0.14.1; extra == "3d"
Requires-Dist: panel; extra == "3d"
Requires-Dist: PVGeo>=2.1.0; extra == "3d"
Requires-Dist: pyacvd>=0.2.9; extra == "3d"
Requires-Dist: PyMCubes; extra == "3d"
Requires-Dist: pymeshfix>=0.15.0; extra == "3d"
Requires-Dist: pythreejs; extra == "3d"
Dynamic: author
Dynamic: author-email
Dynamic: classifier
Dynamic: description
Dynamic: description-content-type
Dynamic: home-page
Dynamic: keywords
Dynamic: license
Dynamic: provides-extra
Dynamic: requires-dist
Dynamic: requires-python
Dynamic: summary
